{
  "meta": {
    "version": "2026-03-07",
    "updated_at": "2026-03-07T14:00:00Z",
    "currency": "USD",
    "schema_version": "1.0",
    "source": "https://taimi.com",
    "maintainer": "Kanto Company",
    "license": "CC BY 4.0",
    "tool_count": 10
  },
  "tool": {
    "slug": "windsurf",
    "name": "Windsurf",
    "vendor": {
      "name": "Cognition AI",
      "hq_country": "US",
      "eu_based": false,
      "pricing_url": "https://windsurf.com/pricing"
    },
    "plans": [
      {
        "id": "windsurf-free",
        "name": "Free",
        "category": "free",
        "base_price": {
          "amount": 0,
          "period": "monthly",
          "per": "user"
        },
        "includes": {
          "premium_requests": null,
          "tokens_included": null,
          "notes": "Limited credits"
        },
        "overage": null
      },
      {
        "id": "windsurf-pro",
        "name": "Pro",
        "category": "individual",
        "base_price": {
          "amount": 15.00,
          "period": "monthly",
          "per": "user"
        },
        "includes": {
          "premium_requests": 500,
          "tokens_included": null,
          "notes": "500 flow credits"
        },
        "overage": null
      },
      {
        "id": "windsurf-teams",
        "name": "Teams",
        "category": "team",
        "base_price": {
          "amount": 30.00,
          "period": "monthly",
          "per": "user"
        },
        "includes": {
          "premium_requests": null,
          "tokens_included": null,
          "notes": "Self-hosted option"
        },
        "overage": null
      }
    ],
    "capabilities": {
      "autonomy_level": "interactive_to_autonomous",
      "ide_type": "ide",
      "model_choice": true,
      "self_hosted": true,
      "fedramp": true,
      "eu_data_residency": true,
      "soc2": true,
      "on_premise": true
    },
    "benchmarks": {
      "swe_bench_verified": 78.0,
      "measured_at": "2026-03-01"
    }
  }
}
